{
  "page-index-hero-image-alt": "imagem de herói da ethereum.org",
  "page-index-meta-description": "A Ethereum é uma plataforma global e descentralizada para dinheiro e novos tipos de aplicativos. Na Ethereum, você pode escrever um código que controle dinheiro e crie aplicativos acessíveis em qualquer lugar do mundo.",
  "page-index-meta-title": "Início",
  "page-index-sections-developers-desc": "Conheça a tecnologia por trás da Ethereum e seus aplicativos, para que você possa começar a construir com ela.",
  "page-index-sections-developers-image-alt": "Ilustração de uma mão que constrói um glyph da Ethereum feito de legos",
  "page-index-sections-developers-link-text": "Começar a construir",
  "page-index-sections-developers-title": "Desenvolvedores",
  "page-index-sections-enterprise-desc": "Veja como a Ethereum pode gerar novos modelos de negócios, reduzir seus custos e manter seu negócio.",
  "page-index-sections-enterprise-image-alt": "Ilustração de um grupo que trabalha em um projeto da Ethereum em torno de um laptop",
  "page-index-sections-enterprise-link-text": "Ethereum para Empresas",
  "page-index-sections-enterprise-title": "Empresas",
  "page-index-sections-individuals-desc": "Conheça Ethereum, Ether, carteiras, tokens e muito mais, para poder começar a usar aplicativos da Ethereum.",
  "page-index-sections-individuals-image-alt": "Ilustração de um cachorro doge sentado em um computador",
  "page-index-sections-individuals-link-text": "Comece a usar a Ethereum",
  "page-index-sections-individuals-title": "Sobre a Ethereum",
  "page-index-subtitle": "Na Ethereum, você pode escrever um código que controla o valor digital, que seja executado exatamente como programado e que esteja acessível em qualquer lugar do mundo.",
  "page-index-title": "A Ethereum é uma plataforma global de código aberto para aplicativos descentralizados."
}
