{
  "comp-tutorial-metadata-minute-read": "хвилин на читання",
  "page-tutorial-listing-policy-intro": "Перш ніж надіслати посібник, будь ласка, <a href=\"/contributing/content-resources/\">ознайомтеся з нашими правилами розміщення</a>.",
  "comp-tutorial-metadata-tip-author": "Віддячити автору",
  "page-tutorial-create-an-issue": "Створити issue",
  "page-tutorial-create-an-issue-desc": "Заповніть шаблон issue, коротко описавши ваш посібник.",
  "page-tutorial-raise-issue-btn": "Відкрити issue",
  "page-tutorial-read-time": "хв",
  "page-tutorial-submit-btn": "Надіслати посібник",
  "page-tutorial-subtitle": "Ласкаво просимо до нашого підібраного списку посібників від спільноти.",
  "page-tutorial-tags-error": "Поки що немає посібників, які б відповідали всім вибраним тегам",
  "page-tutorial-title": "Посібники з розробки для Етеріуму",
  "page-tutorials-meta-description": "Переглядайте та фільтруйте перевірені посібники спільноти Етеріуму за темами.",
  "page-tutorial-external-link": "Зовнішнє посилання",
  "page-tutorials-meta-title": "Посібники з розробки для Етеріуму",
  "page-tutorials-available": "Доступні посібники",
  "page-tutorial-beginner": "Для початківців",
  "page-tutorial-intermediate": "Середній рівень",
  "page-tutorial-advanced": "Просунутий рівень",
  "page-find-wallet-try-removing": "Спробуйте прибрати одну чи дві функції",
  "page-find-wallet-clear": "Очистити фільтри",
  "page-tutorials-env-banner": "Не робіть коміт файлу <code>.env</code>! Будь ласка, ніколи нікому не передавайте та не показуйте свій файл <code>.env</code>, оскільки так ви розкриваєте свої секретні дані. Якщо ви використовуєте систему контролю версій, додайте свій <code>.env</code> до файлу <a href=\"https://git-scm.com/docs/gitignore\">gitignore</a>.",
  "page-tutorial-all": "Усі",
  "page-tutorial-topics": "Теми",
  "page-tutorial-search-placeholder": "Пошук посібників...",
  "page-tutorial-filtering-by": "Фільтрування за:",
  "page-tutorial-more-tags": "ще +{count}"
}