{
  "template-usecase-dropdown-defi": "Decentraliserad finansiering (DeFi)",
  "template-usecase-dropdown-nft": "Icke- utbytbar polletter (NFT)",
  "template-usecase-dropdown-dao": "Decentraliserade oberoende organisationer (DAO)",
  "template-usecase-dropdown-social-networks": "Decentraliserade sociala nätverk",
  "template-usecase-dropdown-identity": "Decentraliserad identitet",
  "template-usecase-dropdown": "Användarfall för Ethereum",
  "template-usecase-banner": "Användningen av Ethereum utvecklas och förändras ständigt. Lägg till information som du tror kommer att göra saker tydligare eller som är mer uppdaterad.",
  "template-usecase-edit-link": "Redigera sida",
  "template-usecase-dropdown-aria": "Använd rullgardinsmenyn för användarfall"
}
