{
  "page-assets-bazaar": "Bazar Ethereum",
  "page-assets-beacon-chain": "Beacon Chain",
  "page-assets-blocks": "Blok penyusun",
  "page-assets-dao": "DAO",
  "page-assets-defi": "DeFi",
  "page-assets-merge": "The Merge",
  "page-assets-doge": "Doge menggunakan dapps",
  "page-assets-download-artist": "Seniman:",
  "page-assets-download-download": "Unduh",
  "page-assets-enterprise": "Ethereum Perusahaan",
  "page-assets-eth": "Ether (ETH)",
  "page-assets-eth-diamond-color": "Berlian ETH (berwarna)",
  "page-assets-eth-diamond-glyph": "Berlian ETH (glif)",
  "page-assets-eth-diamond-gray": "Berlian ETH (abu-abu)",
  "page-assets-eth-diamond-purple": "Berlian ETH (ungu)",
  "page-assets-eth-diamond-white": "Berlian ETH (putih)",
  "page-assets-eth-diamond-colored": "Berlian ETH (berwarna penuh)",
  "page-assets-eth-diamond-colored-svg": "Berlian ETH (berwarna penuh, SVG)",
  "page-assets-eth-glyph-video-dark": "Video glif ETH (gelap)",
  "page-assets-eth-glyph-video-light": "Video glif ETH (terang)",
  "page-assets-eth-logo-landscape-gray": "Logo ETH lanskap (abu-abu)",
  "page-assets-eth-logo-landscape-purple": "Logo ETH lanskap (ungu)",
  "page-assets-eth-logo-landscape-white": "Logo ETH lanskap (putih)",
  "page-assets-eth-logo-portrait-gray": "Logo ETH potret (abu-abu)",
  "page-assets-eth-logo-portrait-purple": "Logo ETH potret (ungu)",
  "page-assets-eth-logo-portrait-white": "Logo ETH potret (putih)",
  "page-assets-eth-wordmark-gray": "Wordmark ETH (abu-abu)",
  "page-assets-eth-wordmark-purple": "Wordmark ETH (ungu)",
  "page-assets-eth-wordmark-white": "Wordmark ETH (putih)",
  "page-assets-ethereum-brand-assets": "Aset \"merek\" Ethereum",
  "page-assets-finance": "Keuangan",
  "page-assets-future": "Masa Depan",
  "page-assets-h1": "Aset ethereum.org",
  "page-assets-hero": "Hero ethereum.org",
  "page-assets-hero-panda": "Hero ethereum.org dengan panda merge",
  "page-assets-merge-panda": "Panda merge",
  "page-assets-merge-panda-svg": "Panda merge SVG",
  "page-assets-hero-particles": "Gambar partikel ETH",
  "page-assets-historical-artwork": "Karya seni bersejarah",
  "page-assets-illustrations": "Ilustrasi",
  "page-assets-impact": "Dampak",
  "page-assets-infrastructure": "Infrastruktur",
  "page-assets-leslie-the-rhino": "Leslie si badak",
  "page-assets-meta-desc": "Jelajahi dan unduh aset merek, ilustrasi, dan media Ethereum dan ethereum.org.",
  "page-assets-meta-title": "Aset merek Ethereum",
  "page-assets-mainnet": "Mainnet",
  "page-assets-page-assets-solid-background": "Latar belakang solid",
  "page-assets-page-assets-transparent-background": "Latar belakang transparan",
  "page-assets-robot": "Dompet robot",
  "page-assets-sharding": "Sharding",
  "page-assets-hackathon": "Hackathon",
  "page-assets-learn-hero-name": "Universitas futuristik",
  "page-assets-community-hero-name": "Pertemuan komunitas",
  "page-assets-quizzes-hero-name": "Taman bermain tak terbatas",
  "page-assets-developers-hero-name": "Membangun masa depan",
  "page-assets-garden-name": "Taman Ethereum",
  "page-assets-roadmap-hero-name": "Jalan menuju masa depan",
  "page-assets-layer-2-hero-name": "Membangun Ethereum",
  "page-assets-guides-hero-name": "Lab Ethereum"
}