{
  "template-usecase-dropdown-ai-agents": "AI ایجنٹس",
  "template-usecase-dropdown-defi": "غیر مرکزی فنانس (DeFi)",
  "template-usecase-dropdown-nft": "نان فنجیبل ٹوکنز (NFTs)",
  "template-usecase-dropdown-dao": "غیر مرکزی خود مختار تنظیمیں (DAOs)",
  "template-usecase-dropdown-apps": "ایتھیریم ایپلی کیشنز",
  "template-usecase-dropdown-payments": "ایتھیریم ادائیگیاں",
  "template-usecase-dropdown-prediction-markets": "پیشین گوئی کی مارکیٹیں",
  "template-usecase-dropdown-social-networks": "غیر مرکزی سوشل نیٹ ورکس",
  "template-usecase-dropdown-restaking": "ری اسٹیکنگ",
  "template-usecase-dropdown-identity": "غیر مرکزی شناخت",
  "template-usecase-dropdown-desci": "غیر مرکزی سائنس (DeSci)",
  "template-usecase-dropdown-refi": "ری جنریٹو فنانس (ReFi)",
  "template-usecase-dropdown": "ایتھیریم کے استعمال کے کیسز",
  "template-usecase-banner": "ایتھیریم کے استعمالات ہمیشہ ترقی کر رہے ہیں اور ارتقاء پذیر ہیں۔ کوئی بھی ایسی معلومات شامل کریں جو آپ کے خیال میں چیزوں کو مزید واضح یا اپ ٹو ڈیٹ بنائے گی۔",
  "template-usecase-edit-link": "صفحہ میں ترمیم کریں",
  "template-usecase-dropdown-aria": "استعمال کے کیس کا ڈراپ ڈاؤن مینو",
  "template-usecase-dropdown-onchain-gaming": "آن چین گیمنگ",
  "template-usecase-dropdown-rwa": "حقیقی دنیا کے اثاثے (RWAs)"
}